lghorizon/__init__.py
lghorizon/const.py
lghorizon/exceptions.py
lghorizon/helpers.py
lghorizon/lghorizon_api.py
lghorizon/models.py
lghorizon/py.typed
lghorizon-0.8.7.dist-info/licenses/LICENSE
lghorizon-0.8.7.dist-info/METADATA
lghorizon-0.8.7.dist-info/WHEEL
lghorizon-0.8.7.dist-info/top_level.txt
lghorizon-0.8.7.dist-info/RECORD
