Metadata-Version: 2.4
Name: lghorizon
Version: 0.8.7
Summary: Python client for Liberty Global Horizon settop boxes
Home-page: https://github.com/sholofly/LGHorizon-python
Author: Rudolf Offereins
Author-email: r.offereins@gmail.com
License: MIT license
Keywords: LG,Horizon,API,Settop box
Classifier: Development Status :: 3 - Alpha
Classifier: Programming Language :: Python :: 3
Classifier: License :: OSI Approved :: MIT License
Classifier: Operating System :: OS Independent
Classifier: Natural Language :: English
Classifier: Intended Audience :: Developers
Classifier: Programming Language :: Python :: 3.6
Classifier: Programming Language :: Python :: 3.7
Classifier: Programming Language :: Python :: 3
Classifier: Topic :: Software Development :: Libraries :: Python Modules
Requires-Python: >=3.9
License-File: LICENSE
Requires-Dist: paho-mqtt
Requires-Dist: requests>=2.22.0
Requires-Dist: backoff>=1.9.0
Dynamic: author
Dynamic: author-email
Dynamic: classifier
Dynamic: description
Dynamic: description-content-type
Dynamic: home-page
Dynamic: keywords
Dynamic: license
Dynamic: license-file
Dynamic: requires-dist
Dynamic: requires-python
Dynamic: summary
